waltz/__init__.py
waltz/__main__.py
waltz/action.py
waltz/build_from_template.py
waltz/command_line.py
waltz/defaults.py
waltz/exceptions.py
waltz/registry.py
waltz/resources.py
waltz/resources/__init__.py
waltz/resources/assignment.py
waltz/resources/blockpy_course.py
waltz/resources/blockpy_group.py
waltz/resources/canvas_resource.py
waltz/resources/gradescope_assignment.py
waltz/resources/gradescope_course.py
waltz/resources/page.py
waltz/resources/problem.py
waltz/resources/quiz.py
waltz/resources/raw.py
waltz/resources/resource.py
waltz/resources/blockpy/blockpy_course.py
waltz/resources/blockpy/blockpy_group.py
waltz/resources/blockpy/blockpy_resource.py
waltz/resources/blockpy/problem.py
waltz/resources/quizzes/__init__.py
waltz/resources/quizzes/essay_question.py
waltz/resources/quizzes/file_upload_question.py
waltz/resources/quizzes/fill_in_multiple_blanks_question.py
waltz/resources/quizzes/matching_question.py
waltz/resources/quizzes/multiple_answers_question.py
waltz/resources/quizzes/multiple_choice_question.py
waltz/resources/quizzes/multiple_dropdowns_question.py
waltz/resources/quizzes/numerical_question.py
waltz/resources/quizzes/quiz_group.py
waltz/resources/quizzes/quiz_question.py
waltz/resources/quizzes/short_answer_question.py
waltz/resources/quizzes/text_only_question.py
waltz/resources/quizzes/true_false_question.py
waltz/services/__init__.py
waltz/services/service.py
waltz/services/blockpy/__init__.py
waltz/services/blockpy/api.py
waltz/services/blockpy/assignment.py
waltz/services/blockpy/blockpy.py
waltz/services/canvas/__init__.py
waltz/services/canvas/api.py
waltz/services/canvas/canvas.py
waltz/services/gradescope/__init__.py
waltz/services/gradescope/gradescope.py
waltz/services/gradescope/pyscope/__init__.py
waltz/services/gradescope/pyscope/account.py
waltz/services/gradescope/pyscope/assignment.py
waltz/services/gradescope/pyscope/course.py
waltz/services/gradescope/pyscope/person.py
waltz/services/gradescope/pyscope/pyscope.py
lms_waltz-0.2.7.dist-info/LICENSE
lms_waltz-0.2.7.dist-info/METADATA
lms_waltz-0.2.7.dist-info/WHEEL
lms_waltz-0.2.7.dist-info/entry_points.txt
lms_waltz-0.2.7.dist-info/top_level.txt
lms_waltz-0.2.7.dist-info/RECORD
