Metadata-Version: 2.1
Name: lms-waltz
Version: 0.2.7
Summary: Coordinate resources between an LMS like Canvas and a local directory
Home-page: https://github.com/acbart/waltz
Author: Austin Cory Bart
Author-email: acbart@udel.edu
License: UNKNOWN
Keywords: lms learning management system curriculum curricular resources
Platform: UNKNOWN
Classifier: Development Status :: 4 - Beta
Classifier: Environment :: Console
Classifier: Intended Audience :: Education
Classifier: Programming Language :: Python :: 3
Classifier: Topic :: Education
Classifier: Topic :: Text Processing :: Markup
Classifier: Topic :: Utilities
Classifier: Operating System :: OS Independent
Classifier: Typing :: Typed
Requires-Python: >=3.6
Requires-Dist: tqdm
Requires-Dist: requests
Requires-Dist: ruamel.yaml
Requires-Dist: jinja2
Requires-Dist: markdown (<3.2)
Requires-Dist: python-frontmatter
Requires-Dist: requests-cache
Requires-Dist: python-dateutil
Requires-Dist: html2text
Requires-Dist: canvasapi
Requires-Dist: tabulate
Requires-Dist: natsort
Requires-Dist: pygments
Requires-Dist: beautifulsoup4
Provides-Extra: dev
Requires-Dist: pyfakefs ; extra == 'dev'
Requires-Dist: wheel ; extra == 'dev'
Requires-Dist: twine ; extra == 'dev'
